europilot/__init__.py
europilot/__version__.py
europilot/compat.py
europilot/controllerstate.py
europilot/exceptions.py
europilot/joystick.py
europilot/print.py
europilot/screen.py
europilot/train.py
europilot-0.0.1.dist-info/METADATA
europilot-0.0.1.dist-info/RECORD
europilot-0.0.1.dist-info/WHEEL
europilot-0.0.1.dist-info/top_level.txt
scripts/__init__.py
scripts/generate_training_data.py
scripts/select_and_grab.py
scripts/select_screen_area.py
scripts/stream_local_screen.py
