Metadata-Version: 2.1
Name: europilot
Version: 0.0.1
Summary: End to end driving simulation inside Euro Truck Simulator 2
Home-page: UNKNOWN
Author: UNKNOWN
Author-email: UNKNOWN
License: UNKNOWN
Platform: UNKNOWN
Requires-Dist: mss (==3.0.1)
Requires-Dist: numpy (>=1.12.1)
Requires-Dist: Pillow (>=4.2.1)
Requires-Dist: pynput (>=1.3.5)
